{
    "packageDirectories": [
        {
            "path": "force-app",
            "default": true
        },
        {
            "path": "b2bSetup",
            "package": "b2bSetup",
            "versionName": "ver 0.1",
            "versionNumber": "0.1.0.NEXT",
            "default": false
        }
    ],
    "name": "B2B-Commerce",
    "namespace": "",
    "sfdcLoginUrl": "https://login.salesforce.com",
    "sourceApiVersion": "55.0",
    "packageAliases": {
        "b2bSetup": "0Ho8c000000GmvsCAC"
    }
}